token_cli/__init__.py
token_cli/main.py
token_cli-0.1.0.dist-info/METADATA
token_cli-0.1.0.dist-info/WHEEL
token_cli-0.1.0.dist-info/entry_points.txt
token_cli-0.1.0.dist-info/top_level.txt
token_cli-0.1.0.dist-info/RECORD
