Metadata-Version: 2.4
Name: token-cli
Version: 0.1.0
Summary: A command-line tool to visualize tokenized text.
Author-email: Taha Yassine <taha.yssne@gmail.com>
License-Expression: MIT
Project-URL: Homepage, https://github.com/taha-yassine/token-cli
Project-URL: Repository, https://github.com/taha-yassine/token-cli
Requires-Python: >=3.9
Requires-Dist: rich>=13.0.0
Requires-Dist: tiktoken>=0.8.0
